qftiful/__init__.py
qftiful-0.0.1.dist-info/LICENSE
qftiful-0.0.1.dist-info/METADATA
qftiful-0.0.1.dist-info/WHEEL
qftiful-0.0.1.dist-info/top_level.txt
qftiful-0.0.1.dist-info/RECORD
